{
    "AX": {
        "error": 0.0033963551638617052, 
        "error_type": "SEM", 
        "filter_outliers_dict": {
            "filter_outliers": true, 
            "iterations": 1, 
            "std_devs": 2
        }, 
        "fit": "Average", 
        "fn": 115, 
        "include_baseline_error": false, 
        "n": 120, 
        "value": -0.07498855278321097
    }, 
    "H1": {
        "error": 0.010825152920636093, 
        "error_type": "SEM", 
        "filter_outliers_dict": {
            "filter_outliers": true, 
            "iterations": 1, 
            "std_devs": 2
        }, 
        "fit": "Average", 
        "fn": 116, 
        "include_baseline_error": false, 
        "n": 120, 
        "value": -0.06826695285191567
    }, 
    "H2": {
        "error": 0.009863652532392627, 
        "error_type": "SEM", 
        "filter_outliers_dict": {
            "filter_outliers": true, 
            "iterations": 1, 
            "std_devs": 2
        }, 
        "fit": "Average", 
        "fn": 116, 
        "include_baseline_error": false, 
        "n": 120, 
        "value": -0.004072488229400639
    }, 
    "L1": {
        "error": 0.01096761500022509, 
        "error_type": "SEM", 
        "filter_outliers_dict": {
            "filter_outliers": true, 
            "iterations": 1, 
            "std_devs": 2
        }, 
        "fit": "Average", 
        "fn": 116, 
        "include_baseline_error": false, 
        "n": 120, 
        "value": -0.14118975322043267
    }, 
    "L2(CDD)": {
        "error": 0.0, 
        "error_type": "SEM", 
        "filter_outliers_dict": {
            "filter_outliers": true, 
            "iterations": 1, 
            "std_devs": 2
        }, 
        "fit": "average", 
        "value": 0.0
    }
}