{
    "AX": {
        "error": 0.004891370828475322,
        "error_type": "SEM",
        "filter_outliers_dict": {
            "filter_outliers": true,
            "iterations": 1,
            "std_devs": 2
        },
        "fit": "Average",
        "fn": 57,
        "include_baseline_error": false,
        "n": 60,
        "reviewed": true,
        "value": -0.07226705530315246
    },
    "H1": {
        "error": 0.01715211499766554,
        "error_type": "SEM",
        "filter_outliers_dict": {
            "filter_outliers": true,
            "iterations": 1,
            "std_devs": 2
        },
        "fit": "Average",
        "fn": 57,
        "include_baseline_error": false,
        "n": 60,
        "reviewed": true,
        "value": -0.032696183362930786
    },
    "H2": {
        "error": 0.012473161467747821,
        "error_type": "SEM",
        "filter_outliers_dict": {
            "filter_outliers": true,
            "iterations": 1,
            "std_devs": 2
        },
        "fit": "Average",
        "fn": 57,
        "include_baseline_error": false,
        "n": 60,
        "reviewed": true,
        "value": -0.234908196094789
    },
    "L1": {
        "error": 0.016160802095418255,
        "error_type": "SEM",
        "filter_outliers_dict": {
            "filter_outliers": true,
            "iterations": 1,
            "std_devs": 2
        },
        "fit": "Average",
        "fn": 59,
        "include_baseline_error": false,
        "n": 60,
        "reviewed": true,
        "value": -0.3986727676149142
    },
    "L2(CDD)": {
        "error": 3.95434404905265e-06,
        "error_type": "SEM",
        "filter_outliers_dict": {
            "filter_outliers": false,
            "iterations": 1,
            "std_devs": 2
        },
        "fit": "Average",
        "fn": 60,
        "include_baseline_error": false,
        "n": 60,
        "reviewed": true,
        "value": 5.640290328301489e-06
    }
}